Hello_fastai/__init__.py
Hello_fastai/_nbdev.py
Hello_fastai/core.py
Hello_fastai-0.0.3.dist-info/LICENSE
Hello_fastai-0.0.3.dist-info/METADATA
Hello_fastai-0.0.3.dist-info/WHEEL
Hello_fastai-0.0.3.dist-info/entry_points.txt
Hello_fastai-0.0.3.dist-info/top_level.txt
Hello_fastai-0.0.3.dist-info/RECORD
