Metadata-Version: 2.1
Name: Hello-fastai
Version: 0.0.3
Summary: Trying new nbdev tool
Home-page: https://github.com/vanhp/Hello_fastai
Author: Vanh
Author-email: kuangphom@gmail.com
License: Apache Software License 2.0
Keywords: nbdev
Platform: UNKNOWN
Classifier: Development Status :: 3 - Alpha
Classifier: Intended Audience :: Developers
Classifier: License :: OSI Approved :: Apache Software License
Classifier: Natural Language :: English
Classifier: Programming Language :: Python :: 3.6
Classifier: Programming Language :: Python :: 3.7
Classifier: Programming Language :: Python :: 3.8
Requires-Python: >=3.6
Requires-Dist: fastcore
